<?xml version="1.0" encoding="UTF-8"?>
<objects serializationModel="Studio.02.02.00">
	<object class="AudioFile" id="{77b98490-07ca-4bee-8a6a-d4b871606473}">
		<property name="assetPath">
			<value>flamethrower.wav</value>
		</property>
		<property name="isStreaming">
			<value>true</value>
		</property>
		<property name="frequencyInKHz">
			<value>44.0999985</value>
		</property>
		<property name="channelCount">
			<value>2</value>
		</property>
		<property name="length">
			<value>13.714285714285714</value>
		</property>
		<relationship name="masterAssetFolder">
			<destination>{e7370b01-df9d-4214-b8ea-5ce32a845d4f}</destination>
		</relationship>
	</object>
</objects>
